<annotation>
	<folder>nsfw</folder>
	<filename>08-23.jpg</filename>
	<path>/Users/noobkenneth/Downloads/nsfw/08-23.jpg</path>
	<source>
		<database>Unknown</database>
	</source>
	<size>
		<width>800</width>
		<height>600</height>
		<depth>3</depth>
	</size>
	<segmented>0</segmented>
	<object>
		<name>breast</name>
		<pose>Unspecified</pose>
		<truncated>0</truncated>
		<difficult>0</difficult>
		<bndbox>
			<xmin>404</xmin>
			<ymin>246</ymin>
			<xmax>462</xmax>
			<ymax>302</ymax>
		</bndbox>
	</object>
	<object>
		<name>breast</name>
		<pose>Unspecified</pose>
		<truncated>0</truncated>
		<difficult>0</difficult>
		<bndbox>
			<xmin>289</xmin>
			<ymin>245</ymin>
			<xmax>344</xmax>
			<ymax>304</ymax>
		</bndbox>
	</object>
	<object>
		<name>vagina</name>
		<pose>Unspecified</pose>
		<truncated>0</truncated>
		<difficult>0</difficult>
		<bndbox>
			<xmin>357</xmin>
			<ymin>380</ymin>
			<xmax>387</xmax>
			<ymax>437</ymax>
		</bndbox>
	</object>
	<object>
		<name>penis</name>
		<pose>Unspecified</pose>
		<truncated>0</truncated>
		<difficult>0</difficult>
		<bndbox>
			<xmin>340</xmin>
			<ymin>441</ymin>
			<xmax>396</xmax>
			<ymax>509</ymax>
		</bndbox>
	</object>
</annotation>
