<annotation>
	<folder>nsfw</folder>
	<filename>10-36.jpg</filename>
	<path>/Users/noobkenneth/Downloads/nsfw/10-36.jpg</path>
	<source>
		<database>Unknown</database>
	</source>
	<size>
		<width>800</width>
		<height>600</height>
		<depth>3</depth>
	</size>
	<segmented>0</segmented>
	<object>
		<name>penis</name>
		<pose>Unspecified</pose>
		<truncated>0</truncated>
		<difficult>0</difficult>
		<bndbox>
			<xmin>51</xmin>
			<ymin>154</ymin>
			<xmax>171</xmax>
			<ymax>241</ymax>
		</bndbox>
	</object>
	<object>
		<name>vagina</name>
		<pose>Unspecified</pose>
		<truncated>0</truncated>
		<difficult>0</difficult>
		<bndbox>
			<xmin>157</xmin>
			<ymin>212</ymin>
			<xmax>193</xmax>
			<ymax>269</ymax>
		</bndbox>
	</object>
</annotation>
