<annotation>
	<folder>nsfw</folder>
	<filename>12-47.jpg</filename>
	<path>/Users/noobkenneth/Downloads/nsfw/12-47.jpg</path>
	<source>
		<database>Unknown</database>
	</source>
	<size>
		<width>800</width>
		<height>600</height>
		<depth>3</depth>
	</size>
	<segmented>0</segmented>
	<object>
		<name>vagina</name>
		<pose>Unspecified</pose>
		<truncated>0</truncated>
		<difficult>0</difficult>
		<bndbox>
			<xmin>295</xmin>
			<ymin>429</ymin>
			<xmax>353</xmax>
			<ymax>482</ymax>
		</bndbox>
	</object>
	<object>
		<name>breast</name>
		<pose>Unspecified</pose>
		<truncated>0</truncated>
		<difficult>0</difficult>
		<bndbox>
			<xmin>270</xmin>
			<ymin>187</ymin>
			<xmax>435</xmax>
			<ymax>285</ymax>
		</bndbox>
	</object>
	<object>
		<name>breast</name>
		<pose>Unspecified</pose>
		<truncated>0</truncated>
		<difficult>0</difficult>
		<bndbox>
			<xmin>550</xmin>
			<ymin>209</ymin>
			<xmax>662</xmax>
			<ymax>305</ymax>
		</bndbox>
	</object>
</annotation>
