<annotation>
	<folder>nsfw</folder>
	<filename>5-26.jpg</filename>
	<path>/Users/noobkenneth/Downloads/nsfw/5-26.jpg</path>
	<source>
		<database>Unknown</database>
	</source>
	<size>
		<width>800</width>
		<height>600</height>
		<depth>3</depth>
	</size>
	<segmented>0</segmented>
	<object>
		<name>breast</name>
		<pose>Unspecified</pose>
		<truncated>0</truncated>
		<difficult>0</difficult>
		<bndbox>
			<xmin>270</xmin>
			<ymin>255</ymin>
			<xmax>457</xmax>
			<ymax>388</ymax>
		</bndbox>
	</object>
	<object>
		<name>breast</name>
		<pose>Unspecified</pose>
		<truncated>0</truncated>
		<difficult>0</difficult>
		<bndbox>
			<xmin>147</xmin>
			<ymin>215</ymin>
			<xmax>291</xmax>
			<ymax>319</ymax>
		</bndbox>
	</object>
</annotation>
