<annotation>
	<folder>nsfw</folder>
	<filename>9viewpornstars_bt4075059.jpg</filename>
	<path>/Users/noobkenneth/Downloads/nsfw/9viewpornstars_bt4075059.jpg</path>
	<source>
		<database>Unknown</database>
	</source>
	<size>
		<width>800</width>
		<height>600</height>
		<depth>3</depth>
	</size>
	<segmented>0</segmented>
	<object>
		<name>breast</name>
		<pose>Unspecified</pose>
		<truncated>0</truncated>
		<difficult>0</difficult>
		<bndbox>
			<xmin>309</xmin>
			<ymin>249</ymin>
			<xmax>483</xmax>
			<ymax>340</ymax>
		</bndbox>
	</object>
	<object>
		<name>breast</name>
		<pose>Unspecified</pose>
		<truncated>0</truncated>
		<difficult>0</difficult>
		<bndbox>
			<xmin>133</xmin>
			<ymin>251</ymin>
			<xmax>290</xmax>
			<ymax>340</ymax>
		</bndbox>
	</object>
</annotation>
